homeassistant_knx_automatic_import.py
hakai_packages/__init__.py
hakai_packages/ha_knx_objects/__init__.py
hakai_packages/ha_knx_objects/ha_knx_cover.py
hakai_packages/ha_knx_objects/ha_knx_date.py
hakai_packages/ha_knx_objects/ha_knx_date_time.py
hakai_packages/ha_knx_objects/ha_knx_expose.py
hakai_packages/ha_knx_objects/ha_knx_light.py
hakai_packages/ha_knx_objects/ha_knx_sensor.py
hakai_packages/ha_knx_objects/ha_knx_switch.py
hakai_packages/ha_knx_objects/ha_knx_time.py
hakai_packages/ha_knx_objects_common/__init__.py
hakai_packages/ha_knx_objects_common/ha_knx_device.py
hakai_packages/ha_knx_objects_common/ha_knx_value_type.py
hakai_packages/ha_knx_objects_factory/__init__.py
hakai_packages/ha_knx_objects_factory/ha_knx_factory.py
hakai_packages/ha_knx_objects_factory/ha_knx_location.py
hakai_packages/hakai_conf/__init__.py
hakai_packages/hakai_conf/hakai_configuration.py
hakai_packages/knx_function_analyzer/__init__.py
hakai_packages/knx_function_analyzer/ha_knx_locations_repository.py
hakai_packages/knx_function_analyzer/knx_space_analyzer.py
hakai_packages/knx_function_analyzer/knx_spaces_repository.py
hakai_packages/knx_project/__init__.py
hakai_packages/knx_project/knx_project_manager.py
hakai_packages/knx_project_objects/__init__.py
hakai_packages/knx_project_objects/knx_com_object.py
hakai_packages/knx_project_objects/knx_dpt_type.py
hakai_packages/knx_project_objects/knx_flags.py
hakai_packages/knx_project_objects/knx_function.py
hakai_packages/knx_project_objects/knx_group_address.py
hakai_packages/knx_project_objects/knx_group_address_ref.py
hakai_packages/knx_project_objects/knx_project_info.py
hakai_packages/knx_project_objects/knx_space.py
hakai_packages/knx_utils/__init__.py
hakai_packages/knx_utils/knx_named_class.py
hakai_packages/knx_utils/knx_tools.py
hakai_packages/knx_utils/serializable.py
homeassistantknxautomaticimport-1.2.2.dist-info/licenses/LICENSE
homeassistantknxautomaticimport-1.2.2.dist-info/METADATA
homeassistantknxautomaticimport-1.2.2.dist-info/WHEEL
homeassistantknxautomaticimport-1.2.2.dist-info/entry_points.txt
homeassistantknxautomaticimport-1.2.2.dist-info/top_level.txt
homeassistantknxautomaticimport-1.2.2.dist-info/RECORD
