Metadata-Version: 2.4
Name: HomeAssistantKNXAutomaticImport
Version: 1.2.2
Summary: HomeAssistantKNXAutomaticImport is a script tool to create configuration file for the Home Assistant KNX integration
Author: marsoupilami
License-Expression: GPL-3.0
Project-URL: Homepage, https://github.com/marsoupilami25/HomeAssitantKnxAutomaticImport
Project-URL: Issues, https://github.com/marsoupilami25/HomeAssitantKnxAutomaticImport/issues
Classifier: Programming Language :: Python :: 3
Classifier: Operating System :: OS Independent
Requires-Python: >=3.10
License-File: LICENSE
Requires-Dist: typer>=0.16
Requires-Dist: classfromtypeddict>=0.0.5
Requires-Dist: xknxproject>=3.8
Requires-Dist: ruamel-yaml>=0.18
Requires-Dist: unidecode>=1.4
Dynamic: license-file
